transkribus_utils/__init__.py
transkribus_utils/cli.py
transkribus_utils/iiif.py
transkribus_utils/mets.py
transkribus_utils/transkribus_utils.py
acdh_transkribus_utils-2.11.dist-info/LICENSE
acdh_transkribus_utils-2.11.dist-info/METADATA
acdh_transkribus_utils-2.11.dist-info/WHEEL
acdh_transkribus_utils-2.11.dist-info/entry_points.txt
acdh_transkribus_utils-2.11.dist-info/top_level.txt
acdh_transkribus_utils-2.11.dist-info/RECORD
