Metadata-Version: 2.1
Name: acdh-transkribus-utils
Version: 2.11
Summary: some utility function to interact with the Transkribus-API
Home-page: https://github.com/acdh-oeaw/acdh-transkribus-utils
Author: Peter Andorfer, Matthias Schlögl, Carl Friedrich Haak
Author-email: peter.andorfer@oeaw.ac.at
License: MIT
Keywords: acdh-transkribus-utils
License-File: LICENSE
Requires-Dist: acdh-xml-pyutils
Requires-Dist: click
